torchEasyTools/__init__.py
torchEasyTools/checkpoint_tools.py
torchEasyTools/model_profile.py
torchEasyTools-1.0.0.dist-info/LICENSE
torchEasyTools-1.0.0.dist-info/METADATA
torchEasyTools-1.0.0.dist-info/WHEEL
torchEasyTools-1.0.0.dist-info/top_level.txt
torchEasyTools-1.0.0.dist-info/RECORD
