Metadata-Version: 2.1
Name: torchEasyTools
Version: 1.0.0
Summary: easy to load pretrain model and compute model complexity
Home-page: https://github.com/Samonsix
Author: samonsix
Author-email: samonsix@163.com
License: UNKNOWN
Keywords: torch profile,torch pretraind,torch model complexity
Platform: UNKNOWN
Requires-Dist: torchvision (>=0.2.1)
Requires-Dist: torch (>=1.0.0)
Requires-Dist: numpy (>=1.19.0)
